cred_switcher/__init__.py
cred_switcher/cli.py
cred_switcher-0.2.1.dist-info/licenses/LICENSE
cred_switcher-0.2.1.dist-info/METADATA
cred_switcher-0.2.1.dist-info/WHEEL
cred_switcher-0.2.1.dist-info/entry_points.txt
cred_switcher-0.2.1.dist-info/top_level.txt
cred_switcher-0.2.1.dist-info/RECORD
