Metadata-Version: 2.4
Name: cred-switcher
Version: 0.2.1
Summary: A CLI tool to switch between Git and AWS credentials
Author: Karizmattic876
License: MIT
Classifier: Programming Language :: Python :: 3
Classifier: License :: OSI Approved :: MIT License
Classifier: Operating System :: OS Independent
License-File: LICENSE
Requires-Dist: pyfiglet
Dynamic: author
Dynamic: classifier
Dynamic: description
Dynamic: description-content-type
Dynamic: license
Dynamic: license-file
Dynamic: requires-dist
Dynamic: summary
